README.md
setup.py
pymecab/__init__.py
pymecab/console.py
pymecab/pymecab.py
pymecab.egg-info/PKG-INFO
pymecab.egg-info/SOURCES.txt
pymecab.egg-info/dependency_links.txt
pymecab.egg-info/entry_points.txt
pymecab.egg-info/requires.txt
pymecab.egg-info/top_level.txt
tests/__init__.py
tests/test_pymecab.py