Metadata-Version: 2.1
Name: pymecab
Version: 2.0.0
Summary: mecab wrapper by using natto-py
Home-page: https://github.com/jxpress/pymecab
Author: JX PRESS Corp.
Author-email: info@jxpress.net
License: MIT License
Keywords: natural language processing,morphological analyzer,mecab
Platform: UNKNOWN
Classifier: Development Status :: 4 - Beta
Classifier: License :: OSI Approved :: MIT License
Classifier: Programming Language :: Python :: 3.7
Classifier: Programming Language :: Python :: 3 :: Only
Provides-Extra: test
